{
  "config": {
    "default": {
      "bluetooth": {
        "primaryService": "heart_rate",
        "characteristic": "heart_rate_measurement",
        "attemptsToFindTheDevice": 5
      },
      "network": { "URI": "http://127.0.0.1", "requestInterval": 500 },
      "serial": { "baudRate": 115200, "delimiter": "\r\n" }
    },
    "user": {
      "bluetooth": {
        "primaryService": "heart_rate",
        "characteristic": "heart_rate_measurement",
        "attemptsToFindTheDevice": 5
      },
      "network": { "URI": "http://127.0.0.1", "requestInterval": 500 },
      "serial": { "baudRate": 115200, "delimiter": "\r\n" }
    }
  },
  "data": []
}
